yangtree/__init__.py
yangtree/__main__.py
yangtree/html.py
yangtree-0.3.0.dist-info/LICENSE
yangtree-0.3.0.dist-info/METADATA
yangtree-0.3.0.dist-info/WHEEL
yangtree-0.3.0.dist-info/entry_points.txt
yangtree-0.3.0.dist-info/top_level.txt
yangtree-0.3.0.dist-info/RECORD
