Metadata-Version: 2.1
Name: yangtree
Version: 0.3.0
Summary: A project for generating YANG tree views.
Author: Joachim Wiberg
License: MIT License
Project-URL: homepage, https://github.com/troglobit/yangtree
Project-URL: repository, https://github.com/troglobit/yangtree
Keywords: YANG,tree,libyang,HTML,jstree
Classifier: Development Status :: 3 - Alpha
Classifier: Intended Audience :: Developers
Classifier: License :: OSI Approved :: MIT License
Classifier: Programming Language :: Python :: 3
Classifier: Programming Language :: Python :: 3.8
Classifier: Programming Language :: Python :: 3.9
Classifier: Programming Language :: Python :: 3.10
Classifier: Topic :: Software Development :: Libraries :: Python Modules
Requires-Python: >=3.8
License-File: LICENSE
Requires-Dist: cffi ==1.16.0
Requires-Dist: libyang ==2.7.1
Requires-Dist: pycparser ==2.22
